hivemind_plus-0.4.4.dist-info/METADATA
hivemind_plus-0.4.4.dist-info/RECORD
hivemind_plus-0.4.4.dist-info/WHEEL
hivemind_plus-0.4.4.dist-info/top_level.txt
hivemindplus/__init__.py
hivemindplus/api.py
hivemindplus/consts.py
hivemindplus/exceptions.py
hivemindplus/helpers.py
hivemindplus/instance.py
hivemindplus/instance_processor.py
hivemindplus/result.py
hivemindplus/result_processor.py
hivemindplus/submission_processor.py
hivemindplus/validation.py
hivemindplus/workflow.py
