Metadata-Version: 2.1
Name: hivemind-plus
Version: 0.4.4
Summary: A workflow wrapper for Hivemind
Home-page: https://bitbucket.org/hvmd/hivemind.plus
Author: Hivemind
Author-email: support@hvmd.io
License: UNKNOWN
Download-URL: https://bitbucket.org/hvmd/hivemind.plus/get/master.tar.gz
Keywords: workflow,tasks
Platform: UNKNOWN
Provides-Extra: test
Requires-Dist: requests
Requires-Dist: python-dateutil
Requires-Dist: pyodbc
Provides-Extra: test
Requires-Dist: pytest; extra == 'test'
Requires-Dist: pytest-mock; extra == 'test'
Requires-Dist: mock; extra == 'test'
Requires-Dist: freezegun; extra == 'test'
Requires-Dist: pyhamcrest; extra == 'test'
